core4ai/__init__.py
core4ai/__main__.py
core4ai/api.py
core4ai/analytics/__init__.py
core4ai/analytics/tracking.py
core4ai/cli/__init__.py
core4ai/cli/commands.py
core4ai/cli/setup.py
core4ai/config/__init__.py
core4ai/config/config.py
core4ai/config/config_manager.py
core4ai/engine/__init__.py
core4ai/engine/models.py
core4ai/engine/processor.py
core4ai/engine/workflow.py
core4ai/prompt_manager/__init__.py
core4ai/prompt_manager/prompt_parser.py
core4ai/prompt_manager/prompt_types.py
core4ai/prompt_manager/registry.py
core4ai/providers/__init__.py
core4ai/providers/base.py
core4ai/providers/ollama_provider.py
core4ai/providers/openai_provider.py
core4ai/providers/utilities.py
core4ai/sample_prompts/code_prompt.md
core4ai/sample_prompts/comparison_prompt.md
core4ai/sample_prompts/cover_letter_prompt.md
core4ai/sample_prompts/creative_prompt.md
core4ai/sample_prompts/data_analysis_prompt.md
core4ai/sample_prompts/email_prompt.md
core4ai/sample_prompts/essay_prompt.md
core4ai/sample_prompts/interview_prompt.md
core4ai/sample_prompts/marketing_prompt.md
core4ai/sample_prompts/product_description_prompt.md
core4ai/sample_prompts/qa_prompt.md
core4ai/sample_prompts/report_prompt.md
core4ai/sample_prompts/research_prompt.md
core4ai/sample_prompts/social_media_prompt.md
core4ai/sample_prompts/summary_prompt.md
core4ai/sample_prompts/syllabus_prompt.md
core4ai/sample_prompts/technical_prompt.md
core4ai/sample_prompts/tutorial_prompt.md
core4ai/utils/__init__.py
core4ai/utils/dashboard.py
core4ai/utils/logging.py
core4ai-1.3.1.dist-info/licenses/LICENSE
core4ai-1.3.1.dist-info/METADATA
core4ai-1.3.1.dist-info/WHEEL
core4ai-1.3.1.dist-info/entry_points.txt
core4ai-1.3.1.dist-info/top_level.txt
core4ai-1.3.1.dist-info/RECORD
