Metadata-Version: 2.4
Name: core4ai
Version: 1.3.1
Summary: Contextual Optimization and Refinement Engine for AI
Author-email: Rahul Pandey <rpandey1901@gmail.com>
License: Apache-2.0
Project-URL: Homepage, https://github.com/iRahulPandey/core4ai
Project-URL: Bug Tracker, https://github.com/iRahulPandey/core4ai/issues
Project-URL: Documentation, https://github.com/iRahulPandey/core4ai#readme
Project-URL: Source Code, https://github.com/iRahulPandey/core4ai
Keywords: llm,prompt,mlflow,ai,ollama,openai,template,analytics
Classifier: Programming Language :: Python :: 3
Classifier: Programming Language :: Python :: 3.8
Classifier: Programming Language :: Python :: 3.9
Classifier: Programming Language :: Python :: 3.10
Classifier: Programming Language :: Python :: 3.11
Classifier: Programming Language :: Python :: 3.12
Classifier: Operating System :: OS Independent
Classifier: Development Status :: 5 - Production/Stable
Classifier: Intended Audience :: Developers
Classifier: Topic :: Software Development :: Libraries :: Python Modules
Classifier: Topic :: Scientific/Engineering :: Artificial Intelligence
Requires-Python: >=3.8
License-File: LICENSE
Requires-Dist: click>=8.0.0
Requires-Dist: langchain==0.3.23
Requires-Dist: langgraph==0.3.31
Requires-Dist: langchain-openai==0.3.14
Requires-Dist: langchain-ollama==0.3.2
Requires-Dist: langchain-core>=0.3.0
Requires-Dist: mlflow<3.0.0,>=2.21.0
Requires-Dist: pydantic>=2.0.0
Requires-Dist: python-dotenv
Requires-Dist: pyyaml
Requires-Dist: requests
Requires-Dist: aiohttp
Requires-Dist: rich>=10.0.0
Requires-Dist: nest-asyncio>=1.5.6
Requires-Dist: importlib-metadata>=4.0.0
Provides-Extra: dev
Requires-Dist: pytest>=7.0.0; extra == "dev"
Requires-Dist: pytest-asyncio>=0.21.0; extra == "dev"
Requires-Dist: pytest-cov>=4.1.0; extra == "dev"
Dynamic: license-file
